kafka_splunk_connector/__init__.py
kafka_splunk_connector/handler.py
kafka_splunk_connector-1.0.6.dist-info/LICENSE
kafka_splunk_connector-1.0.6.dist-info/METADATA
kafka_splunk_connector-1.0.6.dist-info/WHEEL
kafka_splunk_connector-1.0.6.dist-info/top_level.txt
kafka_splunk_connector-1.0.6.dist-info/RECORD
