Metadata-Version: 2.1
Name: kafka-splunk-connector
Version: 1.0.6
Summary: Library that connects the kafka topic to splunk
Home-page: https://github.com/Sathishsathi/kafka_splunk_connector
Author: Sathish
Author-email: sathishsathi500@gmail.com
License: UNKNOWN
Platform: UNKNOWN
Classifier: Programming Language :: Python :: 2
Classifier: Programming Language :: Python :: 2.7
Classifier: Programming Language :: Python :: 3
Classifier: Programming Language :: Python :: 3.7
Classifier: Programming Language :: Python :: 3.6
Classifier: Programming Language :: Python :: Implementation :: CPython
Classifier: Programming Language :: Python :: Implementation :: PyPy
Classifier: License :: OSI Approved :: MIT License
Classifier: Operating System :: OS Independent
Requires-Dist: kafka-python
Requires-Dist: requests
Requires-Dist: logging
Requires-Dist: splunk-hec-handler
